THTools.py
TableHockeyTools/THTools.py
TableHockeyTools/__init__.py
TableHockeyTools-0.1.3.3.dist-info/LICENSE
TableHockeyTools-0.1.3.3.dist-info/METADATA
TableHockeyTools-0.1.3.3.dist-info/WHEEL
TableHockeyTools-0.1.3.3.dist-info/top_level.txt
TableHockeyTools-0.1.3.3.dist-info/RECORD
