Metadata-Version: 2.1
Name: TableHockeyTools
Version: 0.1.3.3
Summary: A collection of tools for working with TableHockey data.
Home-page: https://github.com/Benginy-lab/TableHockeyTools.git
Author: Benjamin Nygard
Author-email: Benjamin.nygard13@gmail.com
License: MIT
Classifier: Development Status :: 2 - Pre-Alpha
Classifier: Topic :: Software Development :: Libraries :: Python Modules
Classifier: Programming Language :: Python :: 3
Classifier: License :: OSI Approved :: MIT License
Classifier: Operating System :: OS Independent
Requires-Python: >=3.6
License-File: LICENSE
Requires-Dist: beautifulsoup4
Requires-Dist: require
